setup.py
parallel_ci_runner/__init__.py
parallel_ci_runner/docker_commands.py
parallel_ci_runner/logger.py
parallel_ci_runner/runner.py
parallel_ci_runner/shell_commands.py
parallel_ci_runner/utils.py
parallel_ci_runner.egg-info/PKG-INFO
parallel_ci_runner.egg-info/SOURCES.txt
parallel_ci_runner.egg-info/dependency_links.txt
parallel_ci_runner.egg-info/top_level.txt