Metadata-Version: 1.0
Name: parallel-ci-runner
Version: 0.1.8
Summary: A framework for defining and running parallel CI tests, with support for docker-compose.
Home-page: https://github.com/dcosson/parallel-ci-runner
Author: Danny Cosson
Author-email: dcosson@gmail.com
License: MIT
Platform: UNKNOWN
